{
	"name": "DS_LKUP_MAX_VALUE",
	"properties": {
		"linkedServiceName": {
			"referenceName": "LS_Parent_Sqlserver_DW",
			"type": "LinkedServiceReference"
		},
		"parameters": {
			"schemaname": {
				"type": "string",
				"defaultValue": "@dataset().schemaname"
			},
			"tablename": {
				"type": "string",
				"defaultValue": "@dataset().tablename"
			}
		},
		"annotations": [],
		"type": "SqlServerTable",
		"schema": [],
		"typeProperties": {
			"schema": {
				"value": "@dataset().schemaname",
				"type": "Expression"
			},
			"table": {
				"value": "@dataset().tablename",
				"type": "Expression"
			}
		}
	},
	"type": "Microsoft.DataFactory/factories/datasets"
}